pawn/__init__.py
pawn/agentic_worlflow.py
pawn/goat_evm_worflow/__init__.py
pawn/goat_evm_worflow/worflow.py
pawn/goat_solana_worflow/__init__.py
pawn/goat_solana_worflow/workflow.py
pawn/hyperliquid_trader_worflow/__init__.py
pawn/hyperliquid_trader_worflow/tools.py
pawn/hyperliquid_trader_worflow/worflow.py
pawn/llamafeed_worflow/__init__.py
pawn/llamafeed_worflow/llamafeed.py
pawn/llamafeed_worflow/worflow.py
pawn_ai-0.0.2.dist-info/licenses/LICENSE
pawn_ai-0.0.2.dist-info/METADATA
pawn_ai-0.0.2.dist-info/WHEEL
pawn_ai-0.0.2.dist-info/top_level.txt
pawn_ai-0.0.2.dist-info/RECORD
