Metadata-Version: 2.4
Name: pawn_ai
Version: 0.0.2
Summary: Precompiled Agents Workflow Network (P.A.W.N.) for building AI-driven, multi-agent crypto systems.
Home-page: https://github.com/Logarithm-Labs/pawn
Author: Logarithm Labs
Author-email: dev@logarithm.fi
Classifier: Programming Language :: Python :: 3
Classifier: License :: OSI Approved :: MIT License
Classifier: Operating System :: OS Independent
Requires-Python: >=3.12
License-File: LICENSE
Requires-Dist: langgraph-supervisor==0.0.16
Provides-Extra: hyperliquid-trader-worflow
Requires-Dist: langchain==0.3.23; extra == "hyperliquid-trader-worflow"
Requires-Dist: langgraph-supervisor==0.0.16; extra == "hyperliquid-trader-worflow"
Requires-Dist: langchain_openai==0.3.12; extra == "hyperliquid-trader-worflow"
Provides-Extra: goat-solana-worflow
Requires-Dist: solana==0.36.6; extra == "goat-solana-worflow"
Requires-Dist: langgraph-supervisor==0.0.16; extra == "goat-solana-worflow"
Requires-Dist: langchain_openai==0.3.12; extra == "goat-solana-worflow"
Requires-Dist: goat-sdk-adapter-langchain==0.1.1; extra == "goat-solana-worflow"
Requires-Dist: goat-sdk-wallet-crossmint==0.1.11; extra == "goat-solana-worflow"
Requires-Dist: goat-sdk-plugin-spl-token==0.1.4; extra == "goat-solana-worflow"
Requires-Dist: goat-sdk-plugin-jupiter==0.1.3; extra == "goat-solana-worflow"
Provides-Extra: goat-evm-worflow
Requires-Dist: web3==7.10.0; extra == "goat-evm-worflow"
Requires-Dist: langgraph-supervisor==0.0.16; extra == "goat-evm-worflow"
Requires-Dist: langchain_openai==0.3.12; extra == "goat-evm-worflow"
Requires-Dist: goat-sdk-plugin-uniswap==0.1.2; extra == "goat-evm-worflow"
Requires-Dist: goat-sdk-adapter-langchain==0.1.1; extra == "goat-evm-worflow"
Requires-Dist: goat-sdk-wallet-crossmint==0.1.11; extra == "goat-evm-worflow"
Provides-Extra: llamafeed-worflow
Requires-Dist: langgraph-supervisor==0.0.16; extra == "llamafeed-worflow"
Requires-Dist: langchain_openai==0.3.12; extra == "llamafeed-worflow"
Dynamic: author
Dynamic: author-email
Dynamic: classifier
Dynamic: description
Dynamic: description-content-type
Dynamic: home-page
Dynamic: license-file
Dynamic: provides-extra
Dynamic: requires-dist
Dynamic: requires-python
Dynamic: summary
